nonebot_plugin_ncm_saying/__init__.py
nonebot_plugin_ncm_saying-0.1.0.dist-info/LICENSE
nonebot_plugin_ncm_saying-0.1.0.dist-info/METADATA
nonebot_plugin_ncm_saying-0.1.0.dist-info/WHEEL
nonebot_plugin_ncm_saying-0.1.0.dist-info/RECORD
