Metadata-Version: 2.1
Name: nonebot-plugin-ncm-saying
Version: 0.1.0
Summary: 一开口就老网抑云了
Author: Ananovo
Author-email: techotaku39@outlook.com
Requires-Python: >=3.8,<4.0
Classifier: Programming Language :: Python :: 3
Classifier: Programming Language :: Python :: 3.8
Classifier: Programming Language :: Python :: 3.9
Classifier: Programming Language :: Python :: 3.10
Classifier: Programming Language :: Python :: 3.11
Requires-Dist: httpx (>=0.23.1,<0.24.0)
Requires-Dist: nonebot-adapter-onebot (>=2.0.0b1,<3.0.0)
Requires-Dist: nonebot2 (>=2.0.0b2,<3.0.0)
